leegs/__init__.py
leegs/__main__.py
leegs/company_scraper.py
leegs/data_storage.py
leegs/download_profile_pics.py
leegs/employee_scraper.py
leegs/gender_detection.py
leegs/helper_funcs.py
leegs/settings.py
leegs-1.3.0.dist-info/METADATA
leegs-1.3.0.dist-info/WHEEL
leegs-1.3.0.dist-info/entry_points.txt
leegs-1.3.0.dist-info/top_level.txt
leegs-1.3.0.dist-info/RECORD
