Metadata-Version: 2.1
Name: leegs
Version: 1.3.0
Summary: A LinkedIn Profile Scraper
Home-page: https://github.com/vidithbalasa/Divercity-Challenge
Author: Vidith Balasa
Author-email: vidithbalasa@gmail.com
License: UNKNOWN
Platform: UNKNOWN
Requires-Python: >=3.10
Requires-Dist: selenium
Requires-Dist: undetected-chromedriver
Requires-Dist: requests
Requires-Dist: pandas
Requires-Dist: numpy
Requires-Dist: tqdm
